httpdummy/__init__.py
httpdummy/server.py
httpdummy-1.1.7.dist-info/LICENSE
httpdummy-1.1.7.dist-info/METADATA
httpdummy-1.1.7.dist-info/WHEEL
httpdummy-1.1.7.dist-info/entry_points.txt
httpdummy-1.1.7.dist-info/top_level.txt
httpdummy-1.1.7.dist-info/RECORD
