Metadata-Version: 2.1
Name: httpdummy
Version: 1.1.7
Summary: A dummy http server that prints requests and responds
Home-page: http://github.com/ksofa2/httpdummy
Author: Kris Steinhoff
Author-email: ksteinhoff@gmail.com
License: Apache 2.0
Platform: UNKNOWN
Requires-Dist: colorama (~=0.4)
Requires-Dist: PyYAML (~=5.3)
Requires-Dist: watchdog (~=0.9)
Requires-Dist: Werkzeug (~=0.16)
